{"6X9ug14yaICFHIpyHW2IQg==":"mbr-1400x935.jpg","WqlyhQt14uN7Z6c0Ln0yXQ==":"mbr-1400x933.jpg","wVzwzb5Uinr2Lcc8QqSy9w==":"mbr-1400x1010.jpg","SO6gWyNuoxTHtngH7l8gnw==":"mbr-2000x1155.jpg","WZp58opYTCHkKV06V+yK0A==":"mbr-2000x1333.jpg","+6f5lQ0L6BdvdJHgw8GKFA==":"mbr-1-2000x1333.jpg","dmCM/kwyDYfl2g0mCOO8ng==":"mbr-2-2000x1333.jpg","rOlQVLSIVIyZDESAMhse4A==":"mbr-3-2000x1333.jpg","z0kNfIkWauTbb3Aemz8bug==":"mbr-2000x1334.jpg","YIo/LSGiovp+BjJz1MIg2w==":"mbr-4-2000x1333.jpg","3vSpZnkm/LU/PJyVEnH7qQ==":"13b91f5797eb30c37fd7975acf140730-1400x934.jpg","Ps1HRbD5tNMrUAtZOnNFLA==":"top-hr-2000x1328.jpg","S0WrxpQ1eaEn9ikTeeucDA==":"trucks1-2000x1500.jpg","VBxq2uV2HY4MtiUSm4OedA==":"mbr-5-2000x1333.jpg"}